a816/__init__.py
a816/cli.py
a816/exceptions.py
a816/program.py
a816/py.typed
a816/symbols.py
a816/writers.py
a816/cpu/__init__.py
a816/cpu/cpu_65c816.py
a816/cpu/mapping.py
a816/parse/__init__.py
a816/parse/codegen.py
a816/parse/errors.py
a816/parse/mzparser.py
a816/parse/nodes.py
a816/parse/parser.py
a816/parse/parser_states.py
a816/parse/scanner.py
a816/parse/scanner_states.py
a816/parse/tokens.py
a816/parse/ast/__init__.py
a816/parse/ast/expression.py
a816/parse/ast/nodes.py
script/__init__.py
script/formulas.py
script/pointers.py
a816-1.0.4.dist-info/METADATA
a816-1.0.4.dist-info/WHEEL
a816-1.0.4.dist-info/entry_points.txt
a816-1.0.4.dist-info/licenses/LICENSE
a816-1.0.4.dist-info/RECORD
