Metadata-Version: 2.4
Name: a816
Version: 1.0.4
Summary: 65c816 patching assembler (Super Famicom)
Project-URL: homepage, https://a816.ringum.net
Project-URL: repository, https://github.com/manz/a816
Author-email: Emmanuel Peralta <manz@ringum.net>
License-Expression: MIT
License-File: LICENSE
Keywords: assembly,romhack,super famicom,supernes
Classifier: Intended Audience :: Developers
Classifier: Operating System :: OS Independent
Classifier: Programming Language :: Python :: 3.10
Requires-Python: >=3.10
